<?xml version='1.0' encoding='UTF-8'?>
<KAF xml:lang="nl">
  <linguisticProcessors layer="text">
    <lp timestamp="2013-01-06T18:36:12CET" version="2.0" name="SentenceTokenizer"/>
  </linguisticProcessors>
  <linguisticProcessors layer="terms">
    <lp timestamp="2013-01-06T18:36:12CET" version="2.0" name="SentenceTokenizer"/>
    <lp timestamp="2013-01-06T18:36:13CET" version="1.0" name="SimplePolarityTagger"/>
  </linguisticProcessors>
  <linguisticProcessor layer="opinions">
    <lp timestamp="2013-01-06T18:36:13CET" version="1.0" name="SimpleOpinionDetector"/>
  </linguisticProcessor>
  <linguisticProcessor layer="properties">
    <lp timestamp="2013-01-06T18:36:13CET" version="1.0" name="SimplePropRecognizer_lookup"/>
  </linguisticProcessor>
  <linguisticProcessor layer="entities">
    <lp timestamp="2013-01-06T18:36:13CET" version="1.0" name="SimpleNER_lookup"/>
  </linguisticProcessor>
  <text>
    <wf wid="w_1" para="1" sent="1">ik</wf>
    <wf wid="w_2" para="1" sent="1">werd</wf>
    <wf wid="w_3" para="1" sent="1">bedonderd</wf>
    <wf wid="w_4" para="1" sent="1">prijs</wf>
    <wf wid="w_5" para="1" sent="1">te</wf>
    <wf wid="w_6" para="1" sent="1">hoog</wf>
    <wf wid="w_7" para="1" sent="1">en</wf>
    <wf wid="w_8" para="1" sent="1">geen</wf>
    <wf wid="w_9" para="1" sent="1">ontbijt</wf>
    <wf wid="w_10" para="1" sent="1">..</wf>
    <wf wid="w_11" para="1" sent="2">Op</wf>
    <wf wid="w_12" para="1" sent="2">het</wf>
    <wf wid="w_13" para="1" sent="2">zelfde</wf>
    <wf wid="w_14" para="1" sent="2">tijd</wf>
    <wf wid="w_15" para="1" sent="2">2</wf>
    <wf wid="w_16" para="1" sent="2">personen</wf>
    <wf wid="w_17" para="1" sent="2">in</wf>
    <wf wid="w_18" para="1" sent="2">het</wf>
    <wf wid="w_19" para="1" sent="2">totaal</wf>
    <wf wid="w_20" para="1" sent="2">,</wf>
    <wf wid="w_21" para="1" sent="2">goedkoper</wf>
    <wf wid="w_22" para="1" sent="2">dan</wf>
    <wf wid="w_23" para="1" sent="2">mij</wf>
    <wf wid="w_24" para="1" sent="2">en</wf>
    <wf wid="w_25" para="1" sent="2">ze</wf>
    <wf wid="w_26" para="1" sent="2">hadden</wf>
    <wf wid="w_27" para="1" sent="2">gratis</wf>
    <wf wid="w_28" para="1" sent="2">ontbijt</wf>
    <wf wid="w_29" para="1" sent="2">,</wf>
    <wf wid="w_30" para="1" sent="2">onbeperkt</wf>
    <wf wid="w_31" para="1" sent="2">koffie</wf>
    <wf wid="w_32" para="1" sent="2">en</wf>
    <wf wid="w_33" para="1" sent="2">thee</wf>
    <wf wid="w_34" para="1" sent="2">,</wf>
    <wf wid="w_35" para="1" sent="2">in</wf>
    <wf wid="w_36" para="1" sent="2">het</wf>
    <wf wid="w_37" para="1" sent="2">luxere</wf>
    <wf wid="w_38" para="1" sent="2">hotel</wf>
    <wf wid="w_39" para="1" sent="2">.</wf>
    <wf wid="w_40" para="1" sent="3">Ik</wf>
    <wf wid="w_41" para="1" sent="3">moest</wf>
    <wf wid="w_42" para="1" sent="3">voor</wf>
    <wf wid="w_43" para="1" sent="3">het</wf>
    <wf wid="w_44" para="1" sent="3">ontbijt</wf>
    <wf wid="w_45" para="1" sent="3">12</wf>
    <wf wid="w_46" para="1" sent="3">,</wf>
    <wf wid="w_47" para="1" sent="3">50</wf>
    <wf wid="w_48" para="1" sent="3">euro</wf>
    <wf wid="w_49" para="1" sent="3">betalen</wf>
    <wf wid="w_50" para="1" sent="3">.</wf>
    <wf wid="w_51" para="1" sent="4">Waar</wf>
    <wf wid="w_52" para="1" sent="4">heb</wf>
    <wf wid="w_53" para="1" sent="4">ik</wf>
    <wf wid="w_54" para="1" sent="4">geslapen</wf>
    <wf wid="w_55" para="1" sent="4">is</wf>
    <wf wid="w_56" para="1" sent="4">geen</wf>
    <wf wid="w_57" para="1" sent="4">hotel</wf>
    <wf wid="w_58" para="1" sent="4">,</wf>
    <wf wid="w_59" para="1" sent="4">het</wf>
    <wf wid="w_60" para="1" sent="4">was</wf>
    <wf wid="w_61" para="1" sent="4">een</wf>
    <wf wid="w_62" para="1" sent="4">kamer</wf>
    <wf wid="w_63" para="1" sent="4">.</wf>
    <wf wid="w_64" para="1" sent="5">100</wf>
    <wf wid="w_65" para="1" sent="5">meter</wf>
    <wf wid="w_66" para="1" sent="5">op</wf>
    <wf wid="w_67" para="1" sent="5">het</wf>
    <wf wid="w_68" para="1" sent="5">straat</wf>
    <wf wid="w_69" para="1" sent="5">moest</wf>
    <wf wid="w_70" para="1" sent="5">ik</wf>
    <wf wid="w_71" para="1" sent="5">lopen</wf>
    <wf wid="w_72" para="1" sent="5">naar</wf>
    <wf wid="w_73" para="1" sent="5">mijn</wf>
    <wf wid="w_74" para="1" sent="5">kamer</wf>
    <wf wid="w_75" para="1" sent="5">te</wf>
    <wf wid="w_76" para="1" sent="5">gaan</wf>
    <wf wid="w_77" para="1" sent="5">.</wf>
  </text>
  <terms>
    <term tid="t_1" lemma="ik" type="open">
      <span>
        <target id="w_1"/>
      </span>
    </term>
    <term tid="t_2" lemma="werd" type="open">
      <span>
        <target id="w_2"/>
      </span>
    </term>
    <term tid="t_3" lemma="bedonderd" type="open">
      <span>
        <target id="w_3"/>
      </span>
    </term>
    <term tid="t_4" lemma="prijs" type="open">
      <span>
        <target id="w_4"/>
      </span>
    </term>
    <term tid="t_5" lemma="te" type="open">
      <span>
        <target id="w_5"/>
      </span>
    </term>
    <term tid="t_6" lemma="hoog" type="open" pos="G">
      <span>
        <target id="w_6"/>
      </span>
      <sentiment polarity="negative" resource="VUA_olery_lexicon_nl_lmf"/>
    </term>
    <term tid="t_7" lemma="en" type="open">
      <span>
        <target id="w_7"/>
      </span>
    </term>
    <term tid="t_8" lemma="geen" type="open">
      <span>
        <target id="w_8"/>
      </span>
      <sentiment sentiment_modifier="shifter" resource="VUA_olery_lexicon_nl_lmf"/>
    </term>
    <term tid="t_9" lemma="ontbijt" type="open">
      <span>
        <target id="w_9"/>
      </span>
    </term>
    <term tid="t_10" lemma=".." type="open">
      <span>
        <target id="w_10"/>
      </span>
    </term>
    <term tid="t_11" lemma="op" type="open">
      <span>
        <target id="w_11"/>
      </span>
    </term>
    <term tid="t_12" lemma="het" type="open">
      <span>
        <target id="w_12"/>
      </span>
    </term>
    <term tid="t_13" lemma="zelfde" type="open">
      <span>
        <target id="w_13"/>
      </span>
    </term>
    <term tid="t_14" lemma="tijd" type="open">
      <span>
        <target id="w_14"/>
      </span>
    </term>
    <term tid="t_15" lemma="2" type="open">
      <span>
        <target id="w_15"/>
      </span>
    </term>
    <term tid="t_16" lemma="personen" type="open">
      <span>
        <target id="w_16"/>
      </span>
    </term>
    <term tid="t_17" lemma="in" type="open">
      <span>
        <target id="w_17"/>
      </span>
    </term>
    <term tid="t_18" lemma="het" type="open">
      <span>
        <target id="w_18"/>
      </span>
    </term>
    <term tid="t_19" lemma="totaal" type="open">
      <span>
        <target id="w_19"/>
      </span>
      <sentiment sentiment_modifier="intensifier" resource="VUA_olery_lexicon_nl_lmf"/>
    </term>
    <term tid="t_20" lemma="," type="open">
      <span>
        <target id="w_20"/>
      </span>
    </term>
    <term tid="t_21" lemma="goedkoper" type="open">
      <span>
        <target id="w_21"/>
      </span>
    </term>
    <term tid="t_22" lemma="dan" type="open">
      <span>
        <target id="w_22"/>
      </span>
    </term>
    <term tid="t_23" lemma="mij" type="open">
      <span>
        <target id="w_23"/>
      </span>
    </term>
    <term tid="t_24" lemma="en" type="open">
      <span>
        <target id="w_24"/>
      </span>
    </term>
    <term tid="t_25" lemma="ze" type="open">
      <span>
        <target id="w_25"/>
      </span>
    </term>
    <term tid="t_26" lemma="hadden" type="open">
      <span>
        <target id="w_26"/>
      </span>
    </term>
    <term tid="t_27" lemma="gratis" type="open" pos="G">
      <span>
        <target id="w_27"/>
      </span>
      <sentiment polarity="positive" resource="VUA_olery_lexicon_nl_lmf"/>
    </term>
    <term tid="t_28" lemma="ontbijt" type="open">
      <span>
        <target id="w_28"/>
      </span>
    </term>
    <term tid="t_29" lemma="," type="open">
      <span>
        <target id="w_29"/>
      </span>
    </term>
    <term tid="t_30" lemma="onbeperkt" type="open" pos="G">
      <span>
        <target id="w_30"/>
      </span>
      <sentiment polarity="positive" resource="VUA_olery_lexicon_nl_lmf"/>
    </term>
    <term tid="t_31" lemma="koffie" type="open">
      <span>
        <target id="w_31"/>
      </span>
    </term>
    <term tid="t_32" lemma="en" type="open">
      <span>
        <target id="w_32"/>
      </span>
    </term>
    <term tid="t_33" lemma="thee" type="open">
      <span>
        <target id="w_33"/>
      </span>
    </term>
    <term tid="t_34" lemma="," type="open">
      <span>
        <target id="w_34"/>
      </span>
    </term>
    <term tid="t_35" lemma="in" type="open">
      <span>
        <target id="w_35"/>
      </span>
    </term>
    <term tid="t_36" lemma="het" type="open">
      <span>
        <target id="w_36"/>
      </span>
    </term>
    <term tid="t_37" lemma="luxere" type="open">
      <span>
        <target id="w_37"/>
      </span>
    </term>
    <term tid="t_38" lemma="hotel" type="open">
      <span>
        <target id="w_38"/>
      </span>
    </term>
    <term tid="t_39" lemma="." type="open">
      <span>
        <target id="w_39"/>
      </span>
    </term>
    <term tid="t_40" lemma="ik" type="open">
      <span>
        <target id="w_40"/>
      </span>
    </term>
    <term tid="t_41" lemma="moest" type="open">
      <span>
        <target id="w_41"/>
      </span>
    </term>
    <term tid="t_42" lemma="voor" type="open">
      <span>
        <target id="w_42"/>
      </span>
    </term>
    <term tid="t_43" lemma="het" type="open">
      <span>
        <target id="w_43"/>
      </span>
    </term>
    <term tid="t_44" lemma="ontbijt" type="open">
      <span>
        <target id="w_44"/>
      </span>
    </term>
    <term tid="t_45" lemma="12" type="open">
      <span>
        <target id="w_45"/>
      </span>
    </term>
    <term tid="t_46" lemma="," type="open">
      <span>
        <target id="w_46"/>
      </span>
    </term>
    <term tid="t_47" lemma="50" type="open">
      <span>
        <target id="w_47"/>
      </span>
    </term>
    <term tid="t_48" lemma="euro" type="open">
      <span>
        <target id="w_48"/>
      </span>
    </term>
    <term tid="t_49" lemma="betalen" type="open">
      <span>
        <target id="w_49"/>
      </span>
    </term>
    <term tid="t_50" lemma="." type="open">
      <span>
        <target id="w_50"/>
      </span>
    </term>
    <term tid="t_51" lemma="waar" type="open">
      <span>
        <target id="w_51"/>
      </span>
    </term>
    <term tid="t_52" lemma="heb" type="open">
      <span>
        <target id="w_52"/>
      </span>
    </term>
    <term tid="t_53" lemma="ik" type="open">
      <span>
        <target id="w_53"/>
      </span>
    </term>
    <term tid="t_54" lemma="geslapen" type="open">
      <span>
        <target id="w_54"/>
      </span>
    </term>
    <term tid="t_55" lemma="is" type="open">
      <span>
        <target id="w_55"/>
      </span>
    </term>
    <term tid="t_56" lemma="geen" type="open">
      <span>
        <target id="w_56"/>
      </span>
      <sentiment sentiment_modifier="shifter" resource="VUA_olery_lexicon_nl_lmf"/>
    </term>
    <term tid="t_57" lemma="hotel" type="open">
      <span>
        <target id="w_57"/>
      </span>
    </term>
    <term tid="t_58" lemma="," type="open">
      <span>
        <target id="w_58"/>
      </span>
    </term>
    <term tid="t_59" lemma="het" type="open">
      <span>
        <target id="w_59"/>
      </span>
    </term>
    <term tid="t_60" lemma="was" type="open">
      <span>
        <target id="w_60"/>
      </span>
    </term>
    <term tid="t_61" lemma="een" type="open">
      <span>
        <target id="w_61"/>
      </span>
    </term>
    <term tid="t_62" lemma="kamer" type="open">
      <span>
        <target id="w_62"/>
      </span>
    </term>
    <term tid="t_63" lemma="." type="open">
      <span>
        <target id="w_63"/>
      </span>
    </term>
    <term tid="t_64" lemma="100" type="open">
      <span>
        <target id="w_64"/>
      </span>
    </term>
    <term tid="t_65" lemma="meter" type="open">
      <span>
        <target id="w_65"/>
      </span>
    </term>
    <term tid="t_66" lemma="op" type="open">
      <span>
        <target id="w_66"/>
      </span>
    </term>
    <term tid="t_67" lemma="het" type="open">
      <span>
        <target id="w_67"/>
      </span>
    </term>
    <term tid="t_68" lemma="straat" type="open">
      <span>
        <target id="w_68"/>
      </span>
    </term>
    <term tid="t_69" lemma="moest" type="open">
      <span>
        <target id="w_69"/>
      </span>
    </term>
    <term tid="t_70" lemma="ik" type="open">
      <span>
        <target id="w_70"/>
      </span>
    </term>
    <term tid="t_71" lemma="lopen" type="open">
      <span>
        <target id="w_71"/>
      </span>
    </term>
    <term tid="t_72" lemma="naar" type="open" pos="G">
      <span>
        <target id="w_72"/>
      </span>
      <sentiment polarity="negative" resource="VUA_olery_lexicon_nl_lmf"/>
    </term>
    <term tid="t_73" lemma="mijn" type="open">
      <span>
        <target id="w_73"/>
      </span>
    </term>
    <term tid="t_74" lemma="kamer" type="open">
      <span>
        <target id="w_74"/>
      </span>
    </term>
    <term tid="t_75" lemma="te" type="open">
      <span>
        <target id="w_75"/>
      </span>
    </term>
    <term tid="t_76" lemma="gaan" type="open">
      <span>
        <target id="w_76"/>
      </span>
    </term>
    <term tid="t_77" lemma="." type="open">
      <span>
        <target id="w_77"/>
      </span>
    </term>
  </terms>
  <entities>
    <entity type="ORG" eid="e_1">
      <span>
        <target id="t_62"/>
      </span>
      <span>
        <target id="t_74"/>
      </span>
    </entity>
    <entity type="PER" eid="e_2">
      <span>
        <target id="t_15"/>
      </span>
    </entity>
  </entities>
  <properties>
    <property type="value_for_money" pid="p_1">
      <span>
        <target id="t_4"/>
      </span>
      <span>
        <target id="t_27"/>
      </span>
      <span>
        <target id="t_48"/>
      </span>
      <span>
        <target id="t_49"/>
      </span>
    </property>
    <property type="location" pid="p_2">
      <span>
        <target id="t_65"/>
      </span>
      <span>
        <target id="t_68"/>
      </span>
    </property>
    <property type="room" pid="p_3">
      <span>
        <target id="t_62"/>
      </span>
      <span>
        <target id="t_74"/>
      </span>
    </property>
    <property type="restaurant" pid="p_4">
      <span>
        <target id="t_9"/>
      </span>
      <span>
        <target id="t_28"/>
      </span>
      <span>
        <target id="t_31"/>
      </span>
      <span>
        <target id="t_33"/>
      </span>
      <span>
        <target id="t_44"/>
      </span>
    </property>
  </properties>
  <opinions>
    <opinion oid="o_1">
      <opinion_holder>
        <span>
          <target id="t_1"/>
        </span>
      </opinion_holder>
      <opinion_target>
        <span>
          <target id="t_9"/>
        </span>
      </opinion_target>
      <opinion_expression polarity="negative" strength="-1">
        <span>
          <target id="t_6"/>
        </span>
      </opinion_expression>
    </opinion>
    <opinion oid="o_2">
      <opinion_target>
        <span>
          <target id="t_28"/>
        </span>
      </opinion_target>
      <opinion_expression polarity="positive" strength="1">
        <span>
          <target id="t_27"/>
        </span>
      </opinion_expression>
    </opinion>
    <opinion oid="o_3">
      <opinion_target>
        <span>
          <target id="t_31"/>
        </span>
      </opinion_target>
      <opinion_expression polarity="positive" strength="1">
        <span>
          <target id="t_30"/>
        </span>
      </opinion_expression>
    </opinion>
    <opinion oid="o_4">
      <opinion_holder>
        <span>
          <target id="t_70"/>
        </span>
      </opinion_holder>
      <opinion_target>
        <span>
          <target id="t_74"/>
        </span>
      </opinion_target>
      <opinion_expression polarity="negative" strength="-1">
        <span>
          <target id="t_72"/>
        </span>
      </opinion_expression>
    </opinion>
  </opinions>
</KAF>
